{"version":1,"resource":"file:///home/anu/Documents/GitHub/Coding/AngularLearn/misc/src/app/Components/forms/forms.component.html","entries":[{"id":"AG6C.html","timestamp":1716355410099},{"id":"n3ho.html","timestamp":1716355470526},{"id":"T8U4.html","timestamp":1716355503314},{"id":"rNNM.html","timestamp":1716355528700},{"id":"JRZg.html","timestamp":1716355547018},{"id":"5Sbr.html","timestamp":1716355596680},{"id":"mzlK.html","timestamp":1716355615997},{"id":"fu8O.html","source":"undoRedo.source","timestamp":1716355620042}]}